cyberbattle/__init__.py
cyberbattle/run.py
cyberbattle/agents/DeepQlearner.py
cyberbattle/agents/GNNlearner.py
cyberbattle/agents/Qlearner.py
cyberbattle/agents/RandomCredLookUp.py
cyberbattle/agents/__init__.py
cyberbattle/agents/utils/__init__.py
cyberbattle/agents/utils/agent_policy.py
cyberbattle/agents/utils/agent_wrapper.py
cyberbattle/agents/utils/plot.py
cyberbattle/env/__init__.py
cyberbattle/env/env_generation/Iterative_defender.py
cyberbattle/env/env_generation/__init__.py
cyberbattle/env/env_generation/actions.py
cyberbattle/env/env_generation/cyber_env.py
cyberbattle/env/env_generation/environment_generation.py
cyberbattle/env/samples/CyberBattleChain.py
cyberbattle/env/samples/CyberBattleTiny.py
cyberbattle/env/samples/CyberBattleTinyDeception.py
cyberbattle/env/samples/CyberBattleToyctf.py
cyberbattle/env/samples/__init__.py
cyberbattle/utils/Interface.py
cyberbattle/utils/__init__.py
cyberbattle/utils/env_processing.py
cyberbattle/utils/eval_functions.py
cyberbattle/utils/objects_and_global_functions.py
cyberbattle-0.0.6.dist-info/LICENSE.md
cyberbattle-0.0.6.dist-info/METADATA
cyberbattle-0.0.6.dist-info/WHEEL
cyberbattle-0.0.6.dist-info/top_level.txt
cyberbattle-0.0.6.dist-info/RECORD
