Metadata-Version: 2.1
Name: cyberbattle
Version: 0.0.6
Summary: Cyber environment in Python with gym like API
Home-page: https://github.com/egrillot/CyberBattleAgents/cyberbattle
Author: Emilien GRILLOT
Author-email: emilien.grillot@polytechnique.edu
License: new BSD
Platform: UNKNOWN
Classifier: Programming Language :: Python :: 3
Classifier: License :: OSI Approved :: MIT License
Classifier: Operating System :: OS Independent
License-File: LICENSE.md
Requires-Dist: boolean.py
Requires-Dist: gym
Requires-Dist: matplotlib
Requires-Dist: networkx
Requires-Dist: numpy
Requires-Dist: tensorflow
Requires-Dist: keras
